wegift.datetimeutil-0.1.0.post1-py3.6-nspkg.pth
wegift/datetimeutil/__init__.py
wegift/datetimeutil/datetimeutil.py
wegift/datetimeutil/tests/__init__.py
wegift/datetimeutil/tests/datetimeutil_test.py
wegift.datetimeutil-0.1.0.post1.dist-info/LICENSE.md
wegift.datetimeutil-0.1.0.post1.dist-info/METADATA
wegift.datetimeutil-0.1.0.post1.dist-info/WHEEL
wegift.datetimeutil-0.1.0.post1.dist-info/namespace_packages.txt
wegift.datetimeutil-0.1.0.post1.dist-info/top_level.txt
wegift.datetimeutil-0.1.0.post1.dist-info/RECORD
